Udility/__init__.py
Udility/diffuser.py
Udility-2.0.dist-info/LICENSE
Udility-2.0.dist-info/METADATA
Udility-2.0.dist-info/WHEEL
Udility-2.0.dist-info/top_level.txt
Udility-2.0.dist-info/RECORD
