Metadata-Version: 2.1
Name: Udility
Version: 2.0
Summary: A diffuser to generate illustrative images based on Meta Llama 3.5.
Home-page: https://github.com/uditakhourii/Udility
Author: Udit Akhouri
Author-email: researchudit@gmail.com
Classifier: Programming Language :: Python :: 3
Classifier: License :: OSI Approved :: MIT License
Classifier: Operating System :: OS Independent
Requires-Python: >=3.6
License-File: LICENSE
Requires-Dist: openai
Requires-Dist: cairosvg
Requires-Dist: Pillow
Requires-Dist: matplotlib
